quickai/__init__.py
quickai/image_classification.py
quickai/text_finetuning.py
quickai/text_inferance.py
quickai/yolo/__init__.py
quickai/yolo/backbone.py
quickai/yolo/common.py
quickai/yolo/config.py
quickai/yolo/dataset.py
quickai/yolo/detect.py
quickai/yolo/detect_custom.py
quickai/yolo/preprocess.py
quickai/yolo/train.py
quickai/yolo/utils.py
quickai/yolo/yolov4.py
quickai-2.0.0.dist-info/LICENSE
quickai-2.0.0.dist-info/METADATA
quickai-2.0.0.dist-info/WHEEL
quickai-2.0.0.dist-info/top_level.txt
quickai-2.0.0.dist-info/RECORD
