Metadata-Version: 2.1
Name: quickai
Version: 2.0.0
Summary: QuickAI is a Python library that makes it extremely easy to experiment with state-of-the-art Machine Learning models.
Home-page: https://github.com/geekjr/quickai
Author: geekjr
Author-email: author@example.com
License: UNKNOWN
Project-URL: Bug Tracker, https://github.com/geekjr/quickai/issues
Platform: UNKNOWN
Classifier: Programming Language :: Python :: 3
Classifier: License :: OSI Approved :: MIT License
Classifier: Operating System :: OS Independent
Requires-Python: >=3.6
License-File: LICENSE
Requires-Dist: scikit-learn
Requires-Dist: numpy
Requires-Dist: matplotlib
Requires-Dist: transformers
Requires-Dist: coremltools
